mcp_prefect/__init__.py
mcp_prefect/artifacts.py
mcp_prefect/block.py
mcp_prefect/concurrency_limits.py
mcp_prefect/deployment.py
mcp_prefect/enums.py
mcp_prefect/envs.py
mcp_prefect/flow.py
mcp_prefect/flow_run.py
mcp_prefect/health_check.py
mcp_prefect/main.py
mcp_prefect/server.py
mcp_prefect/task_run.py
mcp_prefect/variable.py
mcp_prefect/work_pools.py
mcp_prefect/work_queue.py
mcp_prefect/workspace.py
mcp_prefect-0.2.3419.dist-info/METADATA
mcp_prefect-0.2.3419.dist-info/WHEEL
mcp_prefect-0.2.3419.dist-info/entry_points.txt
mcp_prefect-0.2.3419.dist-info/RECORD
