Metadata-Version: 2.4
Name: mcp-prefect
Version: 0.2.3419
Summary: MCP Server for Prefect
Author-email: James Munsch <james.a.munsch@gmail.com>
License: MIT
Requires-Python: >=3.12
Requires-Dist: aiosqlite>=0.21.0
Requires-Dist: alembic>=1.16.5
Requires-Dist: annotated-types>=0.7.0
Requires-Dist: anyio>=4.10.0
Requires-Dist: apprise>=1.9.4
Requires-Dist: asgi-lifespan>=2.1.0
Requires-Dist: asyncpg>=0.30.0
Requires-Dist: attrs>=25.3.0
Requires-Dist: authlib>=1.6.4
Requires-Dist: cachetools>=6.2.0
Requires-Dist: certifi>=2025.8.3
Requires-Dist: cffi>=2.0.0
Requires-Dist: charset-normalizer>=3.4.3
Requires-Dist: click>=8.3.0
Requires-Dist: cloudpickle>=3.1.1
Requires-Dist: colorama>=0.4.6
Requires-Dist: coolname>=2.2.0
Requires-Dist: cryptography>=46.0.1
Requires-Dist: dateparser>=1.2.2
Requires-Dist: deprecated>=1.2.18
Requires-Dist: docker>=7.1.0
Requires-Dist: exceptiongroup>=1.3.0
Requires-Dist: fastapi>=0.117.1
Requires-Dist: fastmcp>=2.12.3
Requires-Dist: fsspec>=2025.9.0
Requires-Dist: graphviz>=0.21
Requires-Dist: greenlet>=3.2.4
Requires-Dist: griffe>=1.14.0
Requires-Dist: h11>=0.16.0
Requires-Dist: h2>=4.3.0
Requires-Dist: hpack>=4.1.0
Requires-Dist: httpcore>=1.0.9
Requires-Dist: httpx-sse>=0.4.1
Requires-Dist: httpx>=0.28.1
Requires-Dist: humanize>=4.13.0
Requires-Dist: hyperframe>=6.1.0
Requires-Dist: idna>=3.10
Requires-Dist: importlib-metadata>=8.7.0
Requires-Dist: jinja2-humanize-extension>=0.4.0
Requires-Dist: jinja2>=3.1.6
Requires-Dist: jsonpatch>=1.33
Requires-Dist: jsonpointer>=3.0.0
Requires-Dist: jsonschema-specifications>=2025.9.1
Requires-Dist: jsonschema>=4.25.1
Requires-Dist: mako>=1.3.10
Requires-Dist: markdown-it-py>=4.0.0
Requires-Dist: markdown>=3.9
Requires-Dist: markupsafe>=3.0.2
Requires-Dist: mcp>=1.14.1
Requires-Dist: mdurl>=0.1.2
Requires-Dist: oauthlib>=3.3.1
Requires-Dist: openapi-pydantic>=0.5.1
Requires-Dist: opentelemetry-api>=1.37.0
Requires-Dist: orjson>=3.11.3
Requires-Dist: packaging>=25.0
Requires-Dist: pathspec>=0.12.1
Requires-Dist: pendulum>=3.1.0
Requires-Dist: pip>=24.2
Requires-Dist: prefect>=3.4.19
Requires-Dist: prometheus-client>=0.23.1
Requires-Dist: pycparser>=2.23
Requires-Dist: pydantic-core>=2.33.2
Requires-Dist: pydantic-extra-types>=2.10.5
Requires-Dist: pydantic-settings>=2.10.1
Requires-Dist: pydantic>=2.11.9
Requires-Dist: pygments>=2.19.2
Requires-Dist: pyproject-freeze>=0.1.1
Requires-Dist: python-dateutil>=2.9.0.post0
Requires-Dist: python-dotenv>=1.1.1
Requires-Dist: python-multipart>=0.0.20
Requires-Dist: python-slugify>=8.0.4
Requires-Dist: python-socks>=2.7.2
Requires-Dist: pytz>=2025.2
Requires-Dist: pyyaml>=6.0.2
Requires-Dist: readchar>=4.2.1
Requires-Dist: referencing>=0.36.2
Requires-Dist: regex>=2025.9.18
Requires-Dist: requests-oauthlib>=2.0.0
Requires-Dist: requests>=2.32.5
Requires-Dist: rfc3339-validator>=0.1.4
Requires-Dist: rich>=14.1.0
Requires-Dist: rpds-py>=0.27.1
Requires-Dist: ruamel-yaml-clib>=0.2.12
Requires-Dist: ruamel-yaml>=0.18.15
Requires-Dist: shellingham>=1.5.4
Requires-Dist: six>=1.17.0
Requires-Dist: sniffio>=1.3.1
Requires-Dist: sqlalchemy>=2.0.43
Requires-Dist: sse-starlette>=3.0.2
Requires-Dist: starlette>=0.48.0
Requires-Dist: text-unidecode>=1.3
Requires-Dist: time-machine>=2.19.0
Requires-Dist: toml>=0.10.2
Requires-Dist: tomlkit>=0.13.2
Requires-Dist: typer>=0.17.4
Requires-Dist: typing-extensions>=4.15.0
Requires-Dist: typing-inspection>=0.4.1
Requires-Dist: tzdata>=2025.2
Requires-Dist: tzlocal>=5.3.1
Requires-Dist: ujson>=5.11.0
Requires-Dist: urllib3>=2.5.0
Requires-Dist: uv>=0.8.19
Requires-Dist: uvicorn>=0.36.0
Requires-Dist: websockets>=15.0.1
Requires-Dist: wrapt>=1.17.3
Requires-Dist: zipp>=3.23.0
Provides-Extra: dev
Requires-Dist: black>=23.0.0; extra == 'dev'
Requires-Dist: isort>=5.0.0; extra == 'dev'
Requires-Dist: mypy>=1.0.0; extra == 'dev'
Requires-Dist: pytest-asyncio>=0.21.1; extra == 'dev'
Requires-Dist: pytest>=7.0.0; extra == 'dev'
